{"date":"2018-10-07","platform":"TV","images":{"small":"https://lain.bgm.tv/pic/cover/s/1d/08/258081_zqDDt.jpg","grid":"https://lain.bgm.tv/pic/cover/g/1d/08/258081_zqDDt.jpg","large":"https://lain.bgm.tv/pic/cover/l/1d/08/258081_zqDDt.jpg","medium":"https://lain.bgm.tv/pic/cover/m/1d/08/258081_zqDDt.jpg","common":"https://lain.bgm.tv/pic/cover/c/1d/08/258081_zqDDt.jpg"},"summary":"本作は、犬猿の仲の上司・羽田野と部下・みのりがカプセルホテルの同室に泊まった一夜から、互いを異性として意識し始め惹かれあっていくラブストーリー。そこにメンズモデルの慧といった登場人物も加わり、タイプの違う男性2人との三角関係や、さまざまな形の密着シチュエーションが描かれる。","name":"終電後､カプセルホテルで、上司に微熱伝わる夜。","name_cn":"末班车后､在胶囊旅馆里､向上司传递微热的夜晚","tags":[{"name":"里番","count":80},{"name":"泡面里番","count":58},{"name":"泡面番","count":55},{"name":"2018年10月","count":41},{"name":"TV","count":26},{"name":"2018","count":25},{"name":"漫改","count":22},{"name":"女性向","count":21},{"name":"彗星社","count":13},{"name":"又是女性向","count":12},{"name":"泡面","count":11},{"name":"漫画改","count":10},{"name":"日本动画","count":4},{"name":"荒木英樹","count":3},{"name":"2018年","count":2},{"name":"僧侣档","count":2},{"name":"八代拓","count":2},{"name":"半里番","count":2},{"name":"纯爱","count":2},{"name":"荒木英树","count":2},{"name":"里","count":2},{"name":"2018年10月番","count":1},{"name":"2018秋","count":1},{"name":"GET","count":1},{"name":"a.Anime","count":1},{"name":"d.短片","count":1},{"name":"f.日本","count":1},{"name":"『TVA』","count":1},{"name":"【ANIME】TV丨日本","count":1},{"name":"已保存","count":1}],"infobox":[{"key":"中文名","value":"末班车后､在胶囊旅馆里､向上司传递微热的夜晚"},{"key":"话数","value":"13"},{"key":"放送开始","value":"2018年10月7日"},{"key":"放送星期","value":"星期日"},{"key":"官方网站","value":"https://shucap.cf-anime.com/"},{"key":"播放电视台","value":"TOKYO MX"},{"key":"播放结束","value":"2018年12月23日"},{"key":"Copyright","value":"©Meg/Suiseisha Inc."},{"key":"原作","value":"Meg"},{"key":"脚本","value":"翌有蔵"},{"key":"色彩设计","value":"ほしのあみ"},{"key":"美术设计","value":"佐久間登"},{"key":"美术监督","value":"李書九"},{"key":"摄影监督","value":"板倉あゆみ"},{"key":"剪辑","value":"新海コウキ"},{"key":"制作协力","value":"NAMU animation"},{"key":"製作","value":"彗星社"},{"key":"サブ衣装デザイン","value":"本間ユカ"}],"rating":{"rank":6651,"total":200,"count":{"1":2,"2":8,"3":16,"4":40,"5":72,"6":44,"7":10,"8":3,"9":1,"10":4},"score":5},"total_episodes":13,"collection":{"on_hold":26,"dropped":50,"wish":74,"collect":342,"doing":22},"id":258081,"eps":13,"volumes":0,"locked":false,"nsfw":false,"type":2}