{"date":"2023-04-12","platform":"WEB","images":{"small":"https://lain.bgm.tv/r/200/pic/cover/l/6b/f3/358558_u1o2R.jpg","grid":"https://lain.bgm.tv/r/100/pic/cover/l/6b/f3/358558_u1o2R.jpg","large":"https://lain.bgm.tv/pic/cover/l/6b/f3/358558_u1o2R.jpg","medium":"https://lain.bgm.tv/r/800/pic/cover/l/6b/f3/358558_u1o2R.jpg","common":"https://lain.bgm.tv/r/400/pic/cover/l/6b/f3/358558_u1o2R.jpg"},"summary":"闫月出回到故乡工作，在入职的公司里认识了新的朋友，在一次进入XY密室馆游玩密室游戏后，他发现自己被密室馆的老板许爱幽所吸引。然而，这却是他陷入一个又一个诡异密室幻境的开始。与此同时，随着闫月出与许爱幽的接触，越来越多的事件接连发生在闫月出的身边，这些事件甚至将他的朋友也卷入其中。闫月出在破解密室与寻找事件黑手的过程中逐渐触碰到了当年那段被隐藏的事件真相……","name":"爱幽的密室","name_cn":"","tags":[{"name":"国产","count":90,"total_cont":0},{"name":"悬疑","count":78,"total_cont":0},{"name":"推理","count":57,"total_cont":0},{"name":"2023年4月","count":35,"total_cont":0},{"name":"漫画改","count":30,"total_cont":0},{"name":"国创","count":27,"total_cont":0},{"name":"有妖气","count":19,"total_cont":0},{"name":"壁水羽","count":15,"total_cont":0},{"name":"中国","count":14,"total_cont":0},{"name":"漫改","count":14,"total_cont":0},{"name":"灵叁伍动画","count":11,"total_cont":0},{"name":"WEB","count":9,"total_cont":0},{"name":"2023","count":7,"total_cont":0},{"name":"动画","count":5,"total_cont":0},{"name":"TV","count":4,"total_cont":0},{"name":"密室","count":3,"total_cont":0},{"name":"爱幽的密室","count":2,"total_cont":0},{"name":"李文武","count":2,"total_cont":0},{"name":"国画","count":1,"total_cont":0},{"name":"国产或合作动画","count":1,"total_cont":0},{"name":"幽舞越山","count":1,"total_cont":0},{"name":"及格","count":1,"total_cont":0},{"name":"长剧集","count":1,"total_cont":0},{"name":"動畫片","count":1,"total_cont":0},{"name":"曾锦峰","count":1,"total_cont":0},{"name":"徐嘉","count":1,"total_cont":0},{"name":"md28223051","count":1,"total_cont":0},{"name":"非日","count":1,"total_cont":0},{"name":"日常","count":1,"total_cont":0},{"name":"国产动画","count":1,"total_cont":0}],"infobox":[{"key":"别名","value":[{"v":"X and Y"}]},{"key":"话数","value":"16"},{"key":"放送开始","value":"2023年4月12日"},{"key":"放送星期","value":"星期三"},{"key":"播放网站","value":"bilibili"},{"key":"导演","value":"徐嘉、李文武"},{"key":"原作","value":"壁水羽、沐芽"},{"key":"出品人","value":"李旎"},{"key":"总制片人","value":"张圣晏"},{"key":"联合制片人","value":"徐嘉"},{"key":"总监制","value":"魔恩·杨璐"},{"key":"制片人","value":"陈卿"},{"key":"制片","value":"田雪姣"},{"key":"文学顾问","value":"壁水羽"},{"key":"脚本","value":"尹仕坦"},{"key":"音乐监制","value":"毕麾"},{"key":"主题歌演出","value":"吴烦（OP）/ 陈乐一（ED）"},{"key":"主题歌作词","value":"李姝"},{"key":"主题歌作曲","value":"吴烦"},{"key":"主题歌编曲","value":"吴烦、刘丞"},{"key":"插入歌演出","value":"钱润玉"},{"key":"执行导演","value":"范友华、唐少生、林佳逊"},{"key":"分镜","value":"李文武、卢杰、梁淦杰、无锡静漫"},{"key":"作画监督","value":"李春茜"},{"key":"色彩设计","value":"梁瑾"},{"key":"背景设定","value":"平方、冯晨旭、安鹏"},{"key":"道具设计","value":"李昕禹、黄恒宇、安鹏、邱咏慧、刘嘉源、袁华、铅魂"},{"key":"3D导演","value":"刘哲全"},{"key":"摄影监督","value":"周宝"},{"key":"剪辑","value":"吴烈伟"},{"key":"摄影","value":"霍志康、张主恩、张主安、姜皓元"},{"key":"OP・ED 分镜","value":"冯静雯、孙景辉"},{"key":"制作协力","value":"梵奇文化、银林动漫、慕初文化、静漫动漫、铅魂动漫、尘行文化"},{"key":"音响监督","value":"毕麾"},{"key":"音乐","value":"吴烦、李嘉宁、GaringLee、刘剑、刘丞"},{"key":"人物设计","value":"曾锦峰"}],"rating":{"rank":5785,"total":187,"count":{"1":2,"2":3,"3":4,"4":8,"5":25,"6":70,"7":50,"8":19,"9":5,"10":1},"score":6.2},"total_episodes":31,"collection":{"on_hold":25,"dropped":32,"wish":134,"collect":258,"doing":68},"id":358558,"eps":16,"meta_tags":["悬疑","推理","漫画改","中国","WEB"],"volumes":0,"series":false,"locked":false,"nsfw":false,"type":2}