{"date":"2024-01-22","platform":"WEB","images":{"small":"https://lain.bgm.tv/r/200/pic/cover/l/71/66/358561_UzsLu.jpg","grid":"https://lain.bgm.tv/r/100/pic/cover/l/71/66/358561_UzsLu.jpg","large":"https://lain.bgm.tv/pic/cover/l/71/66/358561_UzsLu.jpg","medium":"https://lain.bgm.tv/r/800/pic/cover/l/71/66/358561_UzsLu.jpg","common":"https://lain.bgm.tv/r/400/pic/cover/l/71/66/358561_UzsLu.jpg"},"summary":"地球因中子星碎片的出现陷入毁灭危机，以姚源为首的特种部队——黑星小队肩负起拯救人类未来的任务，利用宇宙飞船希望号将大批民众带离地球，于宇宙中寻找新的家园。在冒险与战斗的过程中，姚源等人知晓了更高级的宇宙文明的存在，也认识到了恐怖的事实：宇宙并非乐园，而是充满着黑暗与危险，死亡与恐怖的未知领域。","name":"大宇宙时代","name_cn":"大宇宙时代","tags":[{"name":"国产","count":4},{"name":"中国","count":3},{"name":"太空歌剧","count":2},{"name":"网文改","count":1},{"name":"福煦影视","count":1},{"name":"md28235351","count":1},{"name":"一","count":1},{"name":"动画","count":1},{"name":"TV","count":1},{"name":"科幻","count":1}],"infobox":[{"key":"中文名","value":"大宇宙时代"},{"key":"别名","value":[{"v":"The Age Of Cosmos Exploration"}]},{"key":"话数","value":"12"},{"key":"放送开始","value":"2024年1月22日"},{"key":"放送星期","value":"星期一"},{"key":"原作","value":"zhttty（张恒）"},{"key":"出品人","value":"李旎"},{"key":"总制片人","value":"张圣晏"},{"key":"联合制片人","value":"陈成"},{"key":"总监制","value":"朱贝宁、郑珊珊"},{"key":"制片人","value":"陈卿"},{"key":"执行制片人","value":"蒋竹"},{"key":"制片","value":"陈晓璐、张佶骏，孙朋达、陈雅贤、邵茂奇、吴青娟"},{"key":"版权支持","value":"刘綦、易小丽，潘琳琳、娄婷、姚琼、尹一诺"},{"key":"IP管理与合作总负责","value":"茶仙"},{"key":"IP运营管理","value":"金程、田亿、闻罡、张婧洁，范绮雯、杜明珠、水水、张贤子、苍菂、董亦安、夏飞月、杭晓瑜、郭欣怡、王世浩、申雨晨、李珮瑶、许梅婕、崔晓萌、蔡佳瑾、牛晓娣"},{"key":"内容运营总策划","value":"王蓉、乔理文"},{"key":"内容运营","value":"张天文、吴非晓，徐佳韵、徐晓波、黄珉媛、林姿含、潘紫妍、陈彦霖、傅翀、汪小淇、刘悦"},{"key":"总编审","value":"邓博仁、周奕"},{"key":"编剧","value":"李一诺"},{"key":"执行导演","value":"刘冬晨"},{"key":"音乐导演","value":"魏小涵"},{"key":"导演","value":"杨明丹、曾凡"},{"key":"出品方","value":"江苏幻创动漫文化有限公司(bilibili)"},{"key":"项目支持","value":"杨璐、张璐、田雪姣、褚佳昊、闫明欣、张诗韵、吴静静、蔡怡安"},{"key":"IP授权","value":"谢正瑛、郁晴、夏楠、沈纯、李天骄、曹洁"},{"key":"市场推广总策划","value":"杨亮"},{"key":"市场中心","value":"李周惠子，庄宇童、张蓉坤、景超越、邹文亮、魏文静、刘晟、周锐、罗明天、刘畅、艾予言、杜薇、王星亮、刘佳蕾、阳晓、刘阳、胡令丰"},{"key":"编审","value":"张鑫、胡昊言、石伟华、张禹、郝清扬、张梦儿、卢金苹、明静茹"},{"key":"营销中心","value":"carina、周佳媛、毛建强、崔蓁"},{"key":"音乐中心","value":"谢翔、黄咏竹、吴哲宇"},{"key":"海外发行","value":"亢越、安东、格蕾希、金春成、江桂玲、彭小怡、魏思雨、张仕祺"},{"key":"法务支持","value":"刘楠、程佳昀、裴育"},{"key":"财务支持","value":"樊欣、刘旻昱、张文勤、王通"},{"key":"承制方","value":"福煦影视"},{"key":"总制片","value":"姜冬红、徐礼伟"},{"key":"制片助理","value":"张玲、王丹丹、刘蕊、刘珊、张娜娜、严智芳、吴志凤、梅笑寒、张路、张世杰、王永康、周城、张英江、邵林锋"},{"key":"策划","value":"李一诺、包飞扬、李金瀚"},{"key":"配音导演","value":"黄莺"},{"key":"制作总监","value":"詹长煜"},{"key":"技术总监","value":"严凯"},{"key":"资产负责人","value":"王彦军"},{"key":"绑定负责人","value":"梁兵兵"},{"key":"灯光负责人","value":"许友琴、焦晨飞"},{"key":"音乐制作","value":"周曦、童瑶、穆耸、武树霄、兰晓飞、黄岳、潘明磊、汤嘉颖、曹树衍、刘博元、宋靖、卢延明、吴晓飞"},{"key":"音效制作","value":"杨海平、黄建、徐阳美慧、武树霄、潘明磊、侯子山、魏杰、陈思梦、唐文穗、于刘伟"},{"key":"后期总监","value":"张黎兵、兰晓飞"},{"key":"后期混音","value":"吕萌、魏雅欣、阳光赵、魏杰、北极叶"},{"key":"美术","value":"顾纯存、唐昆凌、李嘉人、郑博文、张丽斯、田杨坤、陈狸猫、孙世超、张十一、李团长、袁艺鸣、杜文轩、张文、葛琳、童童、杨笙、汪婷、金宵、奔奔"},{"key":"分镜","value":"颜昭辉、刘斯宇、铭大智、董发达、王咸朝、刘玺坤、余从锡、龙心悦、苏仕涛、张宇炜、吴涛"},{"key":"资产","value":"张佳鑫、尹顺洁、龚鹤翔、蔡立春、王文佳、邓业荣、饶义洪、张馨冉、杨小龙、杨谦、王月、吴健威、张香香、米亚楠、郭恺、严超、王宁珂、张维康、张修远、周秦山、张利峰、宋欣欣、张文军、徐元浩、夏春银、谭程浩、格勒、李建华"},{"key":"绑定","value":"刘美娜、明月、彭满意、张靖、杨红全、滕金龙、高楠、吴腾飞、罗洁琳"},{"key":"动画","value":"张锋、张晋、王星、赵昊、吕星阳、程方洲、杜营利、李佳乐、李庚、张国、李娜、蒋文、闻博、郑明珠、李欣雨、温晓璇、石钟元、刘少斌、周钰帆、冯佳栋、陈泓予、宋凯南、徐晓晗、吴均达、刘浪、宋敢、黄婉安、陈桂标、廖恒垚、朱幻、杨海宾、蒋少康、岑家宇、陈圣东、王桂林、黄俊、韦邦琴、高丽、朱桂芳、张林串、龚胜、吴国华、王跃杰、卢星明、任俊杰、冉佳荣、龙春阳、张志昕、李竺灵、简林虎、周智国、佘灿树、龙倩、毛恩东云、马福蒂、刘凯凯、谷鑫、吴智源、李思素、艾斌、徐鑫、刘康、尹涛、植中健、王笠阁、徐学川、刘忠宏、旷哲、李东霖、赵宏飞"},{"key":"解算","value":"朱磊、傅永灿、李雨茜、郑志叶、季滨江、韦妗艳、杨晖"},{"key":"特效","value":"徐礼彬、史庭香、叶思汉、张磊、江晨宇、邢锦程、崔锦韬"},{"key":"灯光合成","value":"冯钱富、辛小菊、刘振新、王海南、蒋柯焱、李明煜、夏吟雪、杨卓娜、王发迁、壮家庆、钱思诚、陈文文、韦佳佳、姚茵、李健、金满、许胜、夏勇、孙亚威、李汶东、雷富港、赖金梁、蔡孜晞、赵星钧、王雪峰、黄艺彬、谢鸣枫、何锐韬、周铭驹、龙非、黄纶府、黄家萍、安伟、黄宏翠、胡经纬、刘迎、陈梓燕、王倩、顾琼楠"},{"key":"UE","value":"张钦彭、贾泽华、付阅、刘焘、荀丽、陈鑫彦"},{"key":"剪辑","value":"王家成、刘学艺、卞毅婷、文杨、张洪瑀"},{"key":"校色","value":"李冠冕、郝迪、徐晨幸"}],"rating":{"rank":0,"total":0,"count":{"1":0,"2":0,"3":0,"4":0,"5":0,"6":0,"7":0,"8":0,"9":0,"10":0},"score":0},"total_episodes":12,"collection":{"on_hold":2,"dropped":6,"wish":16,"collect":2,"doing":9},"id":358561,"eps":12,"volumes":0,"locked":false,"nsfw":false,"type":2}