{"date":"2023-10-05","platform":"TV","images":{"small":"https://lain.bgm.tv/r/200/pic/cover/l/db/74/404284_f1616.jpg","grid":"https://lain.bgm.tv/r/100/pic/cover/l/db/74/404284_f1616.jpg","large":"https://lain.bgm.tv/pic/cover/l/db/74/404284_f1616.jpg","medium":"https://lain.bgm.tv/r/800/pic/cover/l/db/74/404284_f1616.jpg","common":"https://lain.bgm.tv/r/400/pic/cover/l/db/74/404284_f1616.jpg"},"summary":"负责铁路运输核心的人偶模块“铁路人偶”。\r\n由于新交通系统的出现而濒临消亡的铁路靠着旅游振兴和商品开发等逐渐恢复，铁路人偶们以进一步促进复兴为目标，集合在第2届铁路人偶高峰会上。\r\n这届高峰会的主题是用声音传达御一夜市的魅力。\r\n铁路人偶们为了寻找自己想录制的声音，挑战了户外现场录音的冒险。","name":"レヱル・ロマネスク2","name_cn":"铁路浪漫谭 第二季","tags":[{"name":"泡面番","count":55},{"name":"2023年10月","count":40},{"name":"GAL改","count":33},{"name":"TV","count":27},{"name":"游戏改","count":26},{"name":"2023","count":22},{"name":"横滨AnimationLABO","count":19},{"name":"爱上火车","count":17},{"name":"日常","count":12},{"name":"CLOUDHEARTS","count":9},{"name":"百合","count":6},{"name":"泡面","count":5},{"name":"箙みちる","count":3},{"name":"日本动画","count":2},{"name":"日本","count":2},{"name":"サエッタ","count":1},{"name":"可独立观赏","count":1},{"name":"saetta","count":1},{"name":"铁路浪漫谭","count":1},{"name":"日泡面番","count":1},{"name":"クラウドハーツ","count":1},{"name":"2023秋","count":1},{"name":"2023年秋","count":1},{"name":"令和","count":1},{"name":"令和3年","count":1},{"name":"横滨动画研究所","count":1},{"name":"続篇","count":1},{"name":"1-100","count":1},{"name":"10月","count":1},{"name":"5","count":1}],"infobox":[{"key":"中文名","value":"铁路浪漫谭 第二季"},{"key":"别名","value":[{"v":"Rail Romanesque 2"}]},{"key":"话数","value":"13"},{"key":"放送开始","value":"2023年10月5日"},{"key":"放送星期","value":"星期四"},{"key":"官方网站","value":"https://railromanesque.jp/anime02/"},{"key":"播放电视台","value":"TOKYO MX"},{"key":"Copyright","value":"©レヱルロマネスク２製作委員会"},{"key":"导演","value":"箙みちる"},{"key":"人物原案","value":"cura、田上俊介"},{"key":"人物设定","value":"佐藤天昭"},{"key":"美术监督","value":"緒方剛(鹿児島ラメカヒリム)"},{"key":"色彩设计","value":"加島優生"},{"key":"动画制作","value":"横浜アニメーションラボ＆クラウドハーツ"},{"key":"製作","value":"レヱル・ロマネスク2製作委員会"},{"key":"企画","value":"進行豹"},{"key":"执行制片人","value":"大西泰平"},{"key":"制片人","value":"木立亮"},{"key":"音乐制作","value":"AYUMI ONE."},{"key":"主题歌编曲","value":"西坂恭平 from STRIKERS"},{"key":"主题歌作曲","value":"西坂恭平 from STRIKERS"},{"key":"主题歌作词","value":"joru from STRIKERS"},{"key":"主题歌演出","value":"Ayumi."}],"rating":{"rank":7955,"total":122,"count":{"1":1,"2":7,"3":10,"4":12,"5":56,"6":24,"7":6,"8":3,"9":1,"10":2},"score":5},"total_episodes":13,"collection":{"on_hold":26,"dropped":40,"wish":165,"collect":174,"doing":43},"id":404284,"eps":13,"volumes":0,"series":false,"locked":false,"nsfw":false,"type":2}