{"date":"2023-10-04","platform":"TV","images":{"small":"https://lain.bgm.tv/r/200/pic/cover/l/d0/9c/406180_zvAgW.jpg","grid":"https://lain.bgm.tv/r/100/pic/cover/l/d0/9c/406180_zvAgW.jpg","large":"https://lain.bgm.tv/pic/cover/l/d0/9c/406180_zvAgW.jpg","medium":"https://lain.bgm.tv/r/800/pic/cover/l/d0/9c/406180_zvAgW.jpg","common":"https://lain.bgm.tv/r/400/pic/cover/l/d0/9c/406180_zvAgW.jpg"},"summary":"スキルの優劣が絶対の世界で、\r\n城の門番であるフェイトは《暴食》という\r\n腹が減るだけのスキルを持ったせいで\r\n最底辺の生活をしいられていた。\r\n\r\n しかしある日、城に侵入した賊を仕留めたことにより\r\n世界が一変する――\r\n\r\n無能と蔑まれた少年の下克上が今始まる――","name":"暴食のベルセルク","name_cn":"暴食狂战士","tags":[{"name":"2023年10月","count":103},{"name":"轻小说改","count":72},{"name":"战斗","count":51},{"name":"异世界","count":47},{"name":"奇幻","count":40},{"name":"TV","count":38},{"name":"A・C・G・T","count":36},{"name":"2023","count":29},{"name":"轻改","count":16},{"name":"逢坂良太","count":15},{"name":"関智一","count":10},{"name":"龙傲天","count":6},{"name":"2023年","count":6},{"name":"日本动画","count":5},{"name":"小说改","count":4},{"name":"未确定","count":3},{"name":"黑妹","count":2},{"name":"2023年秋","count":2},{"name":"國澤真理子","count":2},{"name":"柳沢テツヤ","count":2},{"name":"动画","count":1},{"name":"长剧集","count":1},{"name":"令和5年","count":1},{"name":"TVA-01","count":1},{"name":"后宫","count":1},{"name":"23秋","count":1},{"name":"廁紙","count":1},{"name":"暴食狂战士","count":1},{"name":"外包动画","count":1},{"name":"类异世界","count":1}],"infobox":[{"key":"中文名","value":"暴食狂战士"},{"key":"别名","value":[{"v":"Boushoku no Berserk"},{"v":"Berserk of Gluttony"},{"v":"狂怒的暴食"},{"v":"Berserk of Gluttony"}]},{"key":"话数","value":"12"},{"key":"放送开始","value":"2023年10月4日"},{"key":"放送星期","value":"星期三"},{"key":"官方网站","value":"https://bousyoku-anime.com/"},{"key":"播放电视台","value":"TOKYO MX、サンテレビ、BS11"},{"key":"其他","value":"2023年10月1日（U-NEXT・アニメ放題地上波先行配信）"},{"key":"Copyright","value":"©一色一凛／マイクロマガジン社／暴食のベルセルク製作委員会"},{"key":"原作","value":"一色一凛 (GC ノベルズ『暴食のベルセルク〜俺だけレベルという概念を突破する〜』/マイクロマガジン社刊)"},{"key":"导演","value":"柳沢テツヤ"},{"key":"人物原案","value":"fame"},{"key":"剪辑","value":"新見元希（REAL-T）"},{"key":"制作","value":"制片：ジェンコ"},{"key":"主题歌作曲","value":"ROCK★PANDA、HIPTIP"},{"key":"主题歌作词","value":"ROCK★PANDA、HIPTIP（OP） / 40mP（ED）"},{"key":"主题歌演出","value":"EverdreaM [Misato（松岡美里）& Hitomi（関根瞳）]"},{"key":"製作","value":"暴食のベルセルク製作委員会（ジェンコ、ポニーキャニオン、マイクロマガジン社、Crunchyroll、MUSE、HIAN、日本BS放送、U-NEXT）"},{"key":"企画","value":"井原敦哉、大熊一成、子安喜美子、末平アサ、康振木、宮地大輔、田﨑勝也、堤天心；企画协力：飯島江美子、宮田恭輔"},{"key":"制片人","value":"中尾幸彦、松岡貴徳、関戸公人、臼井久人、楊國祥、木内一雄、大和田智之、金庭こず恵"},{"key":"副制片人","value":"川永和希、菊池貞和、大島靖、髙取昌史、菅朗、中村玖見、杉浦仁司、高彗玲、多田祐一"},{"key":"音乐制作","value":"HIAN"},{"key":"音乐制作人","value":"Daisuke“DAIS” Miyachi"},{"key":"动画制片人","value":"安部正次郎、鈴木誠二"}],"rating":{"rank":7450,"total":184,"count":{"1":2,"2":5,"3":11,"4":30,"5":49,"6":70,"7":12,"8":3,"9":1,"10":1},"score":5.2},"total_episodes":12,"collection":{"on_hold":20,"dropped":91,"wish":151,"collect":33,"doing":606},"id":406180,"eps":12,"volumes":0,"locked":false,"nsfw":false,"type":2}