{"date":"1986-03-31","platform":"TV","images":{"small":"https://lain.bgm.tv/r/200/pic/cover/l/28/f8/313669_S5nwC.jpg","grid":"https://lain.bgm.tv/r/100/pic/cover/l/28/f8/313669_S5nwC.jpg","large":"https://lain.bgm.tv/pic/cover/l/28/f8/313669_S5nwC.jpg","medium":"https://lain.bgm.tv/r/800/pic/cover/l/28/f8/313669_S5nwC.jpg","common":"https://lain.bgm.tv/r/400/pic/cover/l/28/f8/313669_S5nwC.jpg"},"summary":"1986年3月31日（月曜）と同年12月29日（月曜）に、本作を基にした単発テレビアニメ『Mr.ペンペン』と『Mr.ペンペンII』がテレビ朝日系列局で放送された。いずれもテレビ朝日とシンエイ動画の共同製作。放送時間は月曜 19:00 - 20:00 （日本標準時）","name":"Mr.ペンペン","name_cn":"","tags":[{"name":"旧物","count":1},{"name":"SHIN-EI动画","count":1}],"infobox":[{"key":"别名","value":[{"v":"Mr. Pen Pen"}]},{"key":"话数","value":"1"},{"key":"放送开始","value":"1986年3月31日"},{"key":"放送星期","value":"星期一"},{"key":"播放电视台","value":"テレビ朝日系列局"},{"key":"导演","value":"馬場健"},{"key":"脚本","value":"寺田憲史"},{"key":"分镜","value":"竹內大三、須永司"},{"key":"演出","value":"山田雄三、須永司"},{"key":"音乐","value":"渡辺岳夫"},{"key":"人物设定","value":"金沢比呂司"},{"key":"美术监督","value":"河野次郎"},{"key":"作画监督","value":"一川孝久"},{"key":"剪辑","value":"岡安肇、小島俊彦、中葉由美子"},{"key":"主题歌作曲","value":"渡辺岳夫"},{"key":"主题歌作词","value":"室山まゆみ、寺田憲史"},{"key":"录音","value":"AUDIO PLANNING U"},{"key":"製作","value":"テレビ朝日、シンエイ動画"},{"key":"音响监督","value":"浦上靖夫"},{"key":"制片人","value":"木村純一（テレビ朝日）、別府幸司（シンエイ動画）"},{"key":"原作","value":"室山まゆみ（連載・小学館学習雑誌小学二年生）"},{"key":"色彩指定","value":"森千草"},{"key":"特效","value":"柏原満"},{"key":"整音","value":"中戸川次男"},{"key":"现像","value":"東京現像所"},{"key":"标题","value":"道川昭"},{"key":"动画检查","value":"入江康智"},{"key":"主题歌演出","value":"山野さと子"}],"rating":{"rank":0,"total":0,"count":{"1":0,"2":0,"3":0,"4":0,"5":0,"6":0,"7":0,"8":0,"9":0,"10":0},"score":0},"total_episodes":1,"collection":{"on_hold":0,"dropped":4,"wish":4,"collect":1,"doing":0},"id":313669,"eps":1,"volumes":0,"locked":false,"nsfw":false,"type":2}