{"date":"2005-12-17","platform":"剧场版","images":{"small":"https://lain.bgm.tv/r/200/pic/cover/l/1f/c9/120069_6ERL6.jpg","grid":"https://lain.bgm.tv/r/100/pic/cover/l/1f/c9/120069_6ERL6.jpg","large":"https://lain.bgm.tv/pic/cover/l/1f/c9/120069_6ERL6.jpg","medium":"https://lain.bgm.tv/r/800/pic/cover/l/1f/c9/120069_6ERL6.jpg","common":"https://lain.bgm.tv/r/400/pic/cover/l/1f/c9/120069_6ERL6.jpg"},"summary":"　　知名製藥公司-泰達羅斯（Daidalos）的總部發生了一場爆炸案，一個少年被困在崩落的鋼架中無法脫身，生命危在旦夕。此時，在以不追究無照醫療行為的條件下，黑傑克進行了一場任誰都無法想像的「外科手術」…\r\n　　同一災難引發了另一場悲劇：一位母親身受重傷而全身癱瘓，為了不拖累子女，她找來有「死神化身」之稱的奇利柯醫生以求安樂死。另一方面，他的孩子為了救母親，日以繼夜打工存錢，希望黑傑克為母親動手術。看著他們的身影，黑傑克不自覺想起自身的遭遇…\r\n　　兩位醫師，一位要致死，一位要救命，就在秘密之島「伊卡洛斯島」上，黑傑克與奇利柯將展開一場生死攸關的衝擊性對決。爆炸事件的內幕為何？系列史上的最大危機，正一步步向這位天才外科醫生逼近！ ","name":"ブラック・ジャック ふたりの黒い医者","name_cn":"怪医黑杰克 两位神秘医师","tags":[{"name":"剧场版","count":31,"total_cont":0},{"name":"2005","count":18,"total_cont":0},{"name":"手塚PRODUCTION","count":15,"total_cont":0},{"name":"怪医黑杰克","count":11,"total_cont":0},{"name":"漫画改","count":11,"total_cont":0},{"name":"漫改","count":5,"total_cont":0},{"name":"手塚真","count":5,"total_cont":0},{"name":"手塚眞","count":3,"total_cont":0},{"name":"医学","count":3,"total_cont":0},{"name":"手冢治虫","count":3,"total_cont":0},{"name":"手塚プロダクション","count":2,"total_cont":0},{"name":"アニメ映画","count":2,"total_cont":0},{"name":"千葉克彦","count":2,"total_cont":0},{"name":"可看可不看","count":2,"total_cont":0},{"name":"BJ","count":2,"total_cont":0},{"name":"黑杰克","count":2,"total_cont":0},{"name":"2005年","count":2,"total_cont":0},{"name":"TV","count":1,"total_cont":0},{"name":"日本","count":1,"total_cont":0},{"name":"lxy","count":1,"total_cont":0},{"name":"旧物","count":1,"total_cont":0},{"name":"▷未欣赏","count":1,"total_cont":0},{"name":"1分钟弃","count":1,"total_cont":0},{"name":"大塚明夫","count":1,"total_cont":0},{"name":"沒看全","count":1,"total_cont":0},{"name":"TVB","count":1,"total_cont":0},{"name":"治愈","count":1,"total_cont":0},{"name":"剧情","count":1,"total_cont":0},{"name":"2005年12月","count":1,"total_cont":0},{"name":"日本动画","count":1,"total_cont":0}],"infobox":[{"key":"中文名","value":"怪医黑杰克 两位神秘医师"},{"key":"别名","value":[{"v":"Black Jack The Two Doctors Of Darkness"}]},{"key":"上映年度","value":"2005-12-17"},{"key":"片长","value":"93min"},{"key":"话数","value":"1"}],"rating":{"rank":3904,"total":53,"count":{"1":0,"2":0,"3":1,"4":3,"5":6,"6":18,"7":18,"8":5,"9":1,"10":1},"score":6.4},"total_episodes":1,"collection":{"on_hold":0,"dropped":8,"wish":42,"collect":105,"doing":2},"id":120069,"eps":1,"meta_tags":["剧场版"],"volumes":0,"series":false,"locked":false,"nsfw":false,"type":2}