{"date":"2022-10-10","platform":"TV","images":{"small":"https://lain.bgm.tv/r/200/pic/cover/l/b1/d4/374563_ksazP.jpg","grid":"https://lain.bgm.tv/r/100/pic/cover/l/b1/d4/374563_ksazP.jpg","large":"https://lain.bgm.tv/pic/cover/l/b1/d4/374563_ksazP.jpg","medium":"https://lain.bgm.tv/r/800/pic/cover/l/b1/d4/374563_ksazP.jpg","common":"https://lain.bgm.tv/r/400/pic/cover/l/b1/d4/374563_ksazP.jpg"},"summary":"“大叔偶像计划”是满福演艺制作公司为了东山再起而推出的全新偶像计划。\r\n尝尽社会酸甜苦辣的6位大叔，克服了年龄和体力的障碍，努力成为偶像。\r\n为了证明自己无论何时都能接受新的挑战，并且发光发热。\r\n人生濒临绝境的6位大叔现在站了起来！ \r\n即便已经三十过半还是年过四十，但内心永远是少年！ \r\n他们的名字就是“永久少年（Eternal Boys）”！","name":"永久少年 Eternal Boys","name_cn":"永久少年 Eternal Boys","tags":[{"name":"原创","count":30},{"name":"2022年10月","count":27},{"name":"偶像","count":25},{"name":"2022","count":21},{"name":"LINDERFILMS","count":20},{"name":"TV","count":16},{"name":"平川大輔","count":6},{"name":"migmi","count":6},{"name":"女性向","count":6},{"name":"日本动画","count":5},{"name":"2022秋","count":3},{"name":"2022年","count":3},{"name":"うえのきみこ","count":3},{"name":"日本","count":2},{"name":"动画","count":2},{"name":"少年","count":2},{"name":"LIDENFILMS","count":2},{"name":"可重温","count":1},{"name":"2020-2029","count":1},{"name":"23.03.13","count":1},{"name":"Eternal","count":1},{"name":"live可翻跳","count":1},{"name":"2024.06","count":1},{"name":"别具一格","count":1},{"name":"长剧集","count":1},{"name":"TVA-02","count":1},{"name":"半长番","count":1},{"name":"永久少年","count":1},{"name":"2023冬","count":1},{"name":"8","count":1}],"infobox":[{"key":"中文名","value":"永久少年 Eternal Boys"},{"key":"别名","value":[{"v":"Eikyuu Shounen: Eternal Boys"}]},{"key":"话数","value":"24"},{"key":"放送开始","value":"2022年10月10日"},{"key":"放送星期","value":"星期一"},{"key":"官方网站","value":"https://eternalboys.jp"},{"key":"播放电视台","value":"フジテレビ"},{"key":"其他电视台","value":"アニマックス、BSフジ"},{"key":"播放结束","value":"2023年3月27日"},{"key":"其他","value":"2022年9月26日（FOD独占先行配信）"},{"key":"Copyright","value":"© 満プロ / 永久少年プロジェクト"},{"key":"原作","value":"満福芸能プロダクション"},{"key":"导演","value":"migmi"},{"key":"人物设定","value":"朝井聖子；副人物设定：福世真奈美、永川桃子、髙畑かおり、山下芳紀理"},{"key":"人物原案","value":"ma2"},{"key":"製作","value":"永久少年プロジェクト（フジテレビジョン、キングレコード、イオンエンターテイメント、ポリゴン・ピクチュアズ、ウルトラスーパーピクチャーズ、クロックワークス、coly、ムービック、アニマックスブロードキャスト・ジャパン、KADOKAWA）桑田靖（フジテレビ）、村上潔、浅田靖浩、塩田周三、松浦裕暁、藤本款、中島瑞木、國枝信吾、佐々木朗、青柳昌行"},{"key":"总制片人","value":"高瀬透子（统括）"},{"key":"制片人","value":"榎本有希、西川恭平、赤木優子"},{"key":"动画制片人","value":"大山裕一"},{"key":"助理制片人","value":"熊本統夫、大野由紀子、小澤文啓、長谷川陽子、長谷川嘉範、大下梨乃"},{"key":"制作协力","value":"中西豪、木村正典、久田晴喜、伊藤修嗣、榮田悠子、櫻井有沙、守屋秀樹、里見哲朗、武智恒雄、佐々木大地、小島菜奈子、外川明宏、小笠原由紀、佐藤功、間庭秀樹、池上昌平、矢田典、正木大督"},{"key":"宣传","value":"サーティスリー、中愛夏"},{"key":"音乐制片人","value":"斉藤一美"},{"key":"音乐制作","value":"フジパシフィックミュージック"},{"key":"道具设计","value":"原由知、丹羽彩乃"},{"key":"服装设计","value":"髙畑かおり、山下芳紀理"},{"key":"主题歌编曲","value":"Mitsu.J（OP1） / SHOW（OP2） / Erde（ED1） / ALYSA（ED2）"},{"key":"主题歌作曲","value":"Mitsu.J（OP1） / SHOW（OP2） / Erde、Daniel Durn、Katrine\"Neya\"Klith（ED1） / ALYSA、Alfred Chan（ED2）"},{"key":"主题歌作词","value":"Soma Genda（OP1） / SHOW（OP2） / Amon Hayashi（ED）"},{"key":"主题歌演出","value":"Gentlemen(爽田佐和緒、藍染悦郎、井伊蓮司、葉小坂初 / CV. 森久保祥太郎、寺島拓篤、笠間淳、KENN)（OP1） / 永久少年(真田健太郎、石田直樹、浅井悠、今川剛、山中大輔、ニコライ朝倉 / CV.平川大輔、小西克幸、福山潤、浪川大輔、森川智之、東地宏樹)（OP2） / Story of Love(吾妻創輝、小鳥遊賢人、小田桐信長、神楽坂咲楽、東十条知架、リン・ジュンジェ / CV. 小林千晃、仲村宗悟、河本啓佑、堀江瞬、石谷春貴、ランズベリー・アーサー)（ED）"},{"key":"插入歌演出","value":"永久少年(真田健太郎、石田直樹、浅井悠、今川剛、山中大輔、柿崎誠 / CV.平川大輔、小西克幸、福山潤、浪川大輔、森川智之、佐々木望)、Gentlemen(爽田佐和緒、藍染悦郎、井伊蓮司、葉小坂初 / CV. 森久保祥太郎、寺島拓篤、笠間淳、KENN)"}],"rating":{"rank":6914,"total":56,"count":{"1":1,"2":0,"3":3,"4":9,"5":24,"6":14,"7":4,"8":1,"9":0,"10":0},"score":5.1},"total_episodes":54,"collection":{"on_hold":15,"dropped":54,"wish":44,"collect":83,"doing":30},"id":374563,"eps":24,"volumes":0,"series":false,"locked":false,"nsfw":false,"type":2}