{"date":"2023-11-10","platform":"WEB","images":{"small":"https://lain.bgm.tv/r/200/pic/cover/l/05/ad/463539_17808.jpg","grid":"https://lain.bgm.tv/r/100/pic/cover/l/05/ad/463539_17808.jpg","large":"https://lain.bgm.tv/pic/cover/l/05/ad/463539_17808.jpg","medium":"https://lain.bgm.tv/r/800/pic/cover/l/05/ad/463539_17808.jpg","common":"https://lain.bgm.tv/r/400/pic/cover/l/05/ad/463539_17808.jpg"},"summary":"在進行機甲武鬥大會的冠軍戰時，布萊札德突然來襲，十年前他們也曾侵襲而來，但不知為何他們這次就很乾脆地撤退了。然後這樣過了好幾個月的某日，在創世紀特區的里昂一行人正要接受訓練時，天空突然出現異常現象，竟然出現了鏡像世界的里昂他們，這到底是怎麼一回事呢？ ","name":"機甲英雄 機鬥勇者 第2季","name_cn":"机甲英雄 机斗勇者 第2季","tags":[{"name":"2023","count":1},{"name":"2023秋","count":1},{"name":"WEB","count":1},{"name":"Animation","count":1},{"name":"TV","count":1},{"name":"日本","count":1},{"name":"机战","count":1}],"infobox":[{"key":"中文名","value":"机甲英雄 机斗勇者 第2季"},{"key":"话数","value":"8"},{"key":"放送开始","value":"2023年11月10日"},{"key":"放送星期","value":"星期五"},{"key":"播放结束","value":"2023年12月29日"},{"key":"Copyright","value":"(C)IGS"},{"key":"原作","value":"IGS(鈊象電子)"},{"key":"导演","value":"アミノテツロー"},{"key":"人物设定","value":"りお"},{"key":"音响","value":"Stay Luck"},{"key":"CG制片人","value":"露木祐治"}],"rating":{"rank":0,"total":2,"count":{"1":0,"2":0,"3":0,"4":0,"5":2,"6":0,"7":0,"8":0,"9":0,"10":0},"score":5},"total_episodes":8,"collection":{"on_hold":1,"dropped":4,"wish":1,"collect":4,"doing":0},"id":463539,"eps":8,"volumes":0,"series":false,"locked":false,"nsfw":false,"type":2}