{"date":"1995-12-16","platform":"OVA","images":{"small":"https://lain.bgm.tv/r/200/pic/cover/l/06/cd/40931_56C45.jpg","grid":"https://lain.bgm.tv/r/100/pic/cover/l/06/cd/40931_56C45.jpg","large":"https://lain.bgm.tv/pic/cover/l/06/cd/40931_56C45.jpg","medium":"https://lain.bgm.tv/r/800/pic/cover/l/06/cd/40931_56C45.jpg","common":"https://lain.bgm.tv/r/400/pic/cover/l/06/cd/40931_56C45.jpg"},"summary":"名場面を登場人物別に再編集したVHSビデオ作品として『映像白書』が発売された。この作品には特典として「夢夢白書」というオリジナルショートストーリーがあり、本放送や劇場版とは大きく異なるシュールな作風で、脚本は桑原和真役の千葉繁が担当している。","name":"幽☆遊☆白書 映像白書II","name_cn":"幽游白书 映像白书2","tags":[{"name":"OVA","count":23,"total_cont":0},{"name":"富坚义博","count":10,"total_cont":0},{"name":"1995","count":9,"total_cont":0},{"name":"StudioPierrot","count":9,"total_cont":0},{"name":"幽游白书","count":9,"total_cont":0},{"name":"1996","count":5,"total_cont":0},{"name":"漫改","count":3,"total_cont":0},{"name":"ぴえろ","count":3,"total_cont":0},{"name":"日本","count":3,"total_cont":0},{"name":"日本动画","count":3,"total_cont":0},{"name":"动画","count":2,"total_cont":0},{"name":"漫画改","count":2,"total_cont":0},{"name":"大橋志吉","count":1,"total_cont":0},{"name":"佐々木望","count":1,"total_cont":0},{"name":"阿部記之","count":1,"total_cont":0},{"name":"2024","count":1,"total_cont":0},{"name":"旧物","count":1,"total_cont":0},{"name":"童年的经典","count":1,"total_cont":0},{"name":"集锦","count":1,"total_cont":0},{"name":"战斗","count":1,"total_cont":0},{"name":"緒方恵美","count":1,"total_cont":0},{"name":"剧场版","count":1,"total_cont":0},{"name":"漫画","count":1,"total_cont":0},{"name":"补番","count":1,"total_cont":0},{"name":"童年","count":1,"total_cont":0},{"name":"檜山修之","count":1,"total_cont":0}],"infobox":[{"key":"中文名","value":"幽游白书 映像白书2"},{"key":"别名","value":[{"v":"映像白書 ~幽助・桑原・蔵馬・飛影の章~"}]},{"key":"话数","value":"4"},{"key":"发售日","value":"1995年12月16日"},{"key":"结束","value":"1996年2月7日"}],"rating":{"rank":0,"total":50,"count":{"1":0,"2":0,"3":2,"4":1,"5":12,"6":25,"7":4,"8":2,"9":3,"10":1},"score":6},"total_episodes":8,"collection":{"on_hold":5,"dropped":9,"wish":27,"collect":85,"doing":3},"id":40931,"eps":4,"meta_tags":["OVA"],"volumes":0,"series":false,"locked":false,"nsfw":false,"type":2}