{"date":"1991-03-09","platform":"剧场版","images":{"small":"https://lain.bgm.tv/r/200/pic/cover/l/7f/0d/416781_84Kj4.jpg","grid":"https://lain.bgm.tv/r/100/pic/cover/l/7f/0d/416781_84Kj4.jpg","large":"https://lain.bgm.tv/pic/cover/l/7f/0d/416781_84Kj4.jpg","medium":"https://lain.bgm.tv/r/800/pic/cover/l/7f/0d/416781_84Kj4.jpg","common":"https://lain.bgm.tv/r/400/pic/cover/l/7f/0d/416781_84Kj4.jpg"},"summary":"脱走してきた魔法幼稚園からティチアヌ先生がタルるートを迎えに来る。\r\n\r\nそんな中、本丸の母、千鶴が原因不明の高熱に倒れる。その病気は魔法界にある百万年に一度しか実を結ばない命の実しか治せないという。そんなタルるートの弱みに付け込んだティチアヌは千鶴を助ける代わりに魔法界に戻ることを強制的に約束させる。\r\n\r\n偶然、命の実を手に入れるも、地獄界から無敵ロボット、ゴーレムが現れる。彼を倒す為には命の実を使うしかないという。\r\n\r\n果たして本丸とタルるートは世界を、千鶴を救う事が出来るか。","name":"まじかる☆タルるートくん","name_cn":"小魔星","tags":[{"name":"剧场版","count":2,"total_cont":0},{"name":"旧物","count":1,"total_cont":0}],"infobox":[{"key":"中文名","value":"小魔星"},{"key":"别名","value":[{"v":"まじかる☆タルるートくん劇場版"},{"v":"Magical Taruruuto-kun Gekijouban"},{"v":"幻法小魔星剧场版"}]},{"key":"上映年度","value":"1991年3月9日"},{"key":"片长","value":"51分"},{"key":"话数","value":"1"},{"key":"製作","value":"今田智憲、茅野力造"},{"key":"企画","value":"旗野義文、関弘美、週刊少年ジャンプ"},{"key":"製作担当","value":"横井三郎、藤橋秀行"},{"key":"原作","value":"江川達也"},{"key":"导演","value":"山内重保"},{"key":"脚本","value":"菅良幸"},{"key":"音乐","value":"横山菁児"},{"key":"摄影监督","value":"福田岳志、菅谷信行"},{"key":"剪辑","value":"片桐公一"},{"key":"录音","value":"市川修"},{"key":"美术监督","value":"坂本信人"},{"key":"作画监督","value":"大倉雅彦"},{"key":"音效","value":"石野貴久"},{"key":"製作进行","value":"田中浩司、坂本健一"},{"key":"副导演","value":"导演助手：幾原邦彦、木戸睦、岩井隆央"},{"key":"制作","value":"集英社、朝日放送テレビ、東映アニメーション"}],"rating":{"rank":0,"total":2,"count":{"1":0,"2":0,"3":0,"4":0,"5":0,"6":1,"7":0,"8":0,"9":0,"10":1},"score":8},"total_episodes":1,"collection":{"on_hold":0,"dropped":3,"wish":4,"collect":4,"doing":2},"id":416781,"eps":1,"meta_tags":["剧场版"],"volumes":0,"series":false,"locked":false,"nsfw":false,"type":2}