{"date":"2007-04-07","platform":"剧场版","images":{"small":"https://lain.bgm.tv/r/200/pic/cover/l/b5/18/84687_UF0Ag.jpg","grid":"https://lain.bgm.tv/r/100/pic/cover/l/b5/18/84687_UF0Ag.jpg","large":"https://lain.bgm.tv/pic/cover/l/b5/18/84687_UF0Ag.jpg","medium":"https://lain.bgm.tv/r/800/pic/cover/l/b5/18/84687_UF0Ag.jpg","common":"https://lain.bgm.tv/r/400/pic/cover/l/b5/18/84687_UF0Ag.jpg"},"summary":"2002年から放映された美少女SFアニメの人気テレビシリーズ全24話をもとに、新作作画や物語の組み換えを交えながら三部作に構成した劇場版の第1部。テレビ版も担当し、原作者の一人でもある後藤圭二監督によるディレクターズ・カット版となっている。地球人が外宇宙にその文明を広げた遠い未来。人類は宇宙惑星連合を成立させていた。だが惑星国家間の経済紛争は絶えず、その衝突は時に有事にも発展する。そんな問題を実力で解決するのは、銀河通商関税機構“GOTT”に所属する“ES”メンバーと呼ばれる超能力エージェントたちだった。その中の二人、普段は同機関の受付嬢を装うエクレールとリュミエールの美少女コンビは、本来のESメンバーとして、今度の任務に赴くが……。テレビシリーズの第1～11話あたりをベースに再構成。二人の主人公ヒロインのうち、特にエクレールのスーパーレディぶりを強く打ち出す仕上げになっている。中盤には、インターミッション的な仕様で、映画のメインストーリーから外れたテレビ版の名場面集なども紹介し、ファンサービスにつとめている。","name":"KIDDY GRADE -IGNITION-（覚醒編）","name_cn":"天使特警 剧场版 觉醒篇","tags":[{"name":"剧场版","count":24,"total_cont":0},{"name":"百合","count":14,"total_cont":0},{"name":"2007","count":11,"total_cont":0},{"name":"GONZO","count":9,"total_cont":0},{"name":"天使特警","count":6,"total_cont":0},{"name":"平野绫","count":4,"total_cont":0},{"name":"井上喜久子","count":4,"total_cont":0},{"name":"动画","count":4,"total_cont":0},{"name":"KiddyGrade","count":4,"total_cont":0},{"name":"水桥香织","count":1,"total_cont":0},{"name":"若本规夫","count":1,"total_cont":0},{"name":"アニメ映画","count":1,"total_cont":0},{"name":"きむらひでふみ","count":1,"total_cont":0},{"name":"2007年4月","count":1,"total_cont":0},{"name":"永田亮子","count":1,"total_cont":0},{"name":"總篇集","count":1,"total_cont":0},{"name":"平野綾","count":1,"total_cont":0},{"name":"SF","count":1,"total_cont":0},{"name":"OVA","count":1,"total_cont":0},{"name":"福山润","count":1,"total_cont":0},{"name":"石田彰","count":1,"total_cont":0},{"name":"日本动画","count":1,"total_cont":0},{"name":"森川智之","count":1,"total_cont":0},{"name":"科幻","count":1,"total_cont":0},{"name":"後藤圭二","count":1,"total_cont":0}],"infobox":[{"key":"中文名","value":"天使特警 剧场版 觉醒篇"},{"key":"别名","value":[{"v":"キディ・グレイド 劇場版第一部 －イグニッション－（覚醒篇）"},{"v":"Kiddy Grade The Movie Ⅰ 「 IGNITION ( 覚醒編 ) 」"}]},{"key":"上映年度","value":"2007-04-07"},{"key":"片长","value":"90分"},{"key":"话数","value":"1"}],"rating":{"rank":0,"total":33,"count":{"1":0,"2":0,"3":0,"4":3,"5":4,"6":10,"7":8,"8":3,"9":0,"10":5},"score":6.7},"total_episodes":1,"collection":{"on_hold":6,"dropped":9,"wish":48,"collect":63,"doing":5},"id":84687,"eps":1,"meta_tags":["剧场版"],"volumes":0,"series":false,"locked":false,"nsfw":false,"type":2}