{"date":"2021-07-22","platform":"剧场版","images":{"small":"https://lain.bgm.tv/r/200/pic/cover/l/72/f7/286125_wTmev.jpg","grid":"https://lain.bgm.tv/r/100/pic/cover/l/72/f7/286125_wTmev.jpg","large":"https://lain.bgm.tv/pic/cover/l/72/f7/286125_wTmev.jpg","medium":"https://lain.bgm.tv/r/800/pic/cover/l/72/f7/286125_wTmev.jpg","common":"https://lain.bgm.tv/r/400/pic/cover/l/72/f7/286125_wTmev.jpg"},"summary":"「機動戦士ガンダム」の富野由悠季監督が手がけ、2014～15年に放送されたテレビシリーズ「ガンダム Gのレコンギスタ」を再構築した劇場版5部作の第3部。かつての宇宙戦争によって多くの科学技術や知識が失われた、遥か未来の「リギルド・センチュリー（R.C.）」と呼ばれる時代。地球のエネルギーを支える「キャピタル・タワー」を守る組織「キャピタル・ガード」の候補生だった少年ベルリ・ゼナムが、世界の真相や自身の生い立ちを知っていく姿を描く。スペースコロニー国家のトワサンガが、地球への帰還を目指す「レコンギスタ作戦」を開始。ザンクト・ポルトにいるアメリア軍に攻撃を仕掛けてくる。キャピタル・タワーの終着点であり、地球と宇宙をつなぐザンクト・ポルトには、地球内外の4つの勢力が集結。それぞれが権利を主張し、激しく意見を戦わせていた。そんな中、アイーダは真実を求めて月の裏側にあるトワサンガへ向かい、そこでベルリとアイーダに関する驚くべき事実が明らかになる。","name":"劇場版 Gのレコンギスタ III 宇宙からの遺産","name_cn":"剧场版 高达G之复国运动 III 来自宇宙的遗产","tags":[{"name":"剧场版","count":114},{"name":"SUNRISE","count":95},{"name":"富野由悠季","count":87},{"name":"高达","count":66},{"name":"2021","count":65},{"name":"原创","count":45},{"name":"萝卜","count":44},{"name":"科幻","count":26},{"name":"机战","count":19},{"name":"GUNDAM","count":10},{"name":"吉田健一","count":9},{"name":"日本动画","count":4},{"name":"サンライズ","count":3},{"name":"日本","count":2},{"name":"动画","count":2},{"name":"2020-2029","count":2},{"name":"2021年","count":2},{"name":"续作","count":2},{"name":"Gのレコンギスタ","count":2},{"name":"Theater","count":1},{"name":"战争","count":1},{"name":"7.5","count":1},{"name":"脇顯太朗","count":1},{"name":"アニメ映画","count":1},{"name":"宇宙","count":1},{"name":"2020s","count":1},{"name":"20s","count":1},{"name":"红萝卜与白萝卜","count":1},{"name":"机甲","count":1},{"name":"2024","count":1}],"infobox":[{"key":"中文名","value":"剧场版 高达G之复国运动 III 来自宇宙的遗产"},{"key":"别名","value":[{"v":"劇場版 ガンダム Gのレコンギスタ III 宇宙からの遺産"},{"v":"剧场版 G之复国运动 III 来自宇宙的遗产"}]},{"key":"上映年度","value":"2021年7月22日"},{"key":"话数","value":"1"}],"rating":{"rank":994,"total":255,"count":{"1":0,"2":0,"3":0,"4":2,"5":8,"6":20,"7":82,"8":114,"9":26,"10":3},"score":7.5},"total_episodes":1,"collection":{"on_hold":17,"dropped":18,"wish":193,"collect":367,"doing":16},"id":286125,"eps":1,"volumes":0,"series":false,"locked":false,"nsfw":false,"type":2}