{"date":"1997-04-19","platform":"剧场版","images":{"small":"https://lain.bgm.tv/pic/cover/s/6e/83/8971_B3aA0.jpg","grid":"https://lain.bgm.tv/pic/cover/g/6e/83/8971_B3aA0.jpg","large":"https://lain.bgm.tv/pic/cover/l/6e/83/8971_B3aA0.jpg","medium":"https://lain.bgm.tv/pic/cover/m/6e/83/8971_B3aA0.jpg","common":"https://lain.bgm.tv/pic/cover/c/6e/83/8971_B3aA0.jpg"},"summary":"","name":"クレヨンしんちゃん 暗黒タマタマ大追跡","name_cn":"蜡笔小新之黑暗珠珠大追击","tags":[{"name":"剧场版","count":52},{"name":"蜡笔小新","count":43},{"name":"1997","count":20},{"name":"搞笑","count":19},{"name":"SHIN-EI","count":8},{"name":"漫画改","count":8},{"name":"シンエイ動画","count":7},{"name":"童年系","count":6},{"name":"日本","count":5},{"name":"00前","count":4},{"name":"アニメ映画","count":3},{"name":"原创","count":2},{"name":"原恵一","count":2},{"name":"日本动画","count":2},{"name":"映画","count":2},{"name":"童年","count":2},{"name":"蠟筆小新","count":2},{"name":"A.E.","count":1},{"name":"SHIN-EI动画","count":1},{"name":"ならはしみき","count":1},{"name":"劇場版","count":1},{"name":"动画","count":1},{"name":"动画电影","count":1},{"name":"原惠一","count":1},{"name":"奇幻","count":1},{"name":"汤浅政明","count":1},{"name":"漫改","count":1},{"name":"现实世界","count":1},{"name":"矢島晶子","count":1},{"name":"藤原啓治","count":1}],"infobox":[{"key":"中文名","value":"蜡笔小新之黑暗珠珠大追击"},{"key":"上映年度","value":"1997-04-19"},{"key":"片长","value":"100min"},{"key":"导演","value":"原恵一"},{"key":"原作","value":"臼井儀人"},{"key":"脚本","value":"原恵一"},{"key":"分镜","value":"原恵一"},{"key":"演出","value":"水島努"},{"key":"人物设定","value":"原勝徳"},{"key":"作画监督","value":[{"v":"原勝徳"},{"v":"堤のりゆき"}]},{"key":"音乐","value":[{"v":"荒川敏行"},{"v":"宮崎慎二"}]},{"key":"美術監督","value":[{"v":"野村可南子"},{"v":"古賀徹"}]},{"key":"設定デザイン","value":"湯浅政明"},{"key":"ねんどアニメ","value":"石田卓也"},{"key":"色彩設計","value":"野中幸子"},{"key":"色指定","value":"森田晋次"},{"key":"话数","value":"1"}],"rating":{"rank":3324,"total":124,"count":{"1":0,"2":3,"3":1,"4":1,"5":13,"6":28,"7":58,"8":15,"9":2,"10":3},"score":6.6},"total_episodes":1,"collection":{"on_hold":4,"dropped":7,"wish":20,"collect":218,"doing":4},"id":8971,"eps":1,"volumes":0,"locked":false,"nsfw":false,"type":2}