{"date":"2021-09-10","platform":"OVA","images":{"small":"https://lain.bgm.tv/pic/cover/s/f3/fc/330394_3FtE7.jpg","grid":"https://lain.bgm.tv/pic/cover/g/f3/fc/330394_3FtE7.jpg","large":"https://lain.bgm.tv/pic/cover/l/f3/fc/330394_3FtE7.jpg","medium":"https://lain.bgm.tv/pic/cover/m/f3/fc/330394_3FtE7.jpg","common":"https://lain.bgm.tv/pic/cover/c/f3/fc/330394_3FtE7.jpg"},"summary":"“その猟団に、ひかれてはならぬ。\"\r\n\r\nカルタフィルスがひとときの午睡につき、チセが学院の聴講生となる少し前。\r\n\r\n学院への招待が届き、不安ながらも準備を進めるチセと手伝うエリアス達。\r\n久しくなかった日常の最中、不気味な馬を連れたスプリガンが邸宅を訪れる。\r\n『今回の亡霊猟団の様子がおかしい』という言葉と共に。\r\n\r\n――倫敦から移り住んできた普通の少年・ガブリエルは退屈していた。\r\n自身の境遇、友人との別離、不慣れな土地、すべてに。\r\nそれらから逃れるように眺めた窓の先、一瞬見えた紫煙を追いかけて家を抜け出た、その時。\r\n本来なら交わらぬはずの少年の世界は、厚いベールの裏側に生きる魔法使い達の世界と交わり始める……。\r\n\r\n原作漫画16~18卷特装版附OAD。描述智世成为学院旁听生之前的事情，故事从带着令人感到害怕的马匹来到宅邸的斯普利甘，表示亡灵猎团的状况有点奇怪而展开。另一边，因为自己的生活、与朋友的别离、不习惯的土地等，对一切感到无趣的普通少年加百列（ガブリエル）也与魔法的世界相遇……","name":"魔法使いの嫁 西の少年と青嵐の騎士","name_cn":"魔法使的新娘 西之少年与青岚的骑士","tags":[{"name":"OAD","count":51},{"name":"2021","count":43},{"name":"StudioKAFKA","count":30},{"name":"漫画改","count":26},{"name":"魔法使的新娘","count":18},{"name":"OVA","count":18},{"name":"奇幻","count":17},{"name":"魔法使いの嫁","count":12},{"name":"漫改","count":8},{"name":"寺澤和晃","count":7},{"name":"竹内良太","count":6},{"name":"恋爱","count":5},{"name":"2021年","count":4},{"name":"治愈","count":3},{"name":"2021年10月","count":2},{"name":"日本动画","count":2},{"name":"续作","count":2},{"name":"未定档","count":1},{"name":"2021年9月","count":1},{"name":"松本淳一","count":1},{"name":"Fall_2021","count":1},{"name":"寺泽和晃","count":1},{"name":"可独立观赏","count":1},{"name":"21夏","count":1},{"name":"種崎敦美","count":1},{"name":"冒险","count":1},{"name":"7","count":1},{"name":"新番","count":1},{"name":"后宫","count":1},{"name":"卖肉","count":1}],"infobox":[{"key":"中文名","value":"魔法使的新娘 西之少年与青岚的骑士"},{"key":"话数","value":"3"},{"key":"发售日","value":"2021年9月10日"},{"key":"官方网站","value":"https://magus-bride.jp/wildhunt/"},{"key":"开始","value":"2021年9月10日"},{"key":"结束","value":"2022年9月9日"},{"key":"Copyright","value":"© 2016 MAG Garden corp. All rights Reserved."},{"key":"原作","value":"ヤマザキコレ「魔法使いの嫁」（ブレイドコミックス / マッグガーデン刊）"},{"key":"导演","value":"寺澤和晃"},{"key":"动画制作","value":"スタジオカフカ（Studio KAFKA）"},{"key":"制作","value":"魔法使いの嫁 OAD 製作委員会"},{"key":"CGI导演","value":"宮地克明"},{"key":"人物设定","value":"加藤寛崇"}],"rating":{"rank":1498,"total":59,"count":{"1":0,"2":0,"3":0,"4":0,"5":2,"6":12,"7":22,"8":15,"9":1,"10":7},"score":7.4},"total_episodes":3,"collection":{"on_hold":41,"dropped":8,"wish":262,"collect":51,"doing":148},"id":330394,"eps":3,"volumes":0,"locked":false,"nsfw":false,"type":2}