{"date":"2019-01-08","platform":"TV","images":{"small":"https://lain.bgm.tv/pic/cover/s/28/a4/250514_BNBt6.jpg","grid":"https://lain.bgm.tv/pic/cover/g/28/a4/250514_BNBt6.jpg","large":"https://lain.bgm.tv/pic/cover/l/28/a4/250514_BNBt6.jpg","medium":"https://lain.bgm.tv/pic/cover/m/28/a4/250514_BNBt6.jpg","common":"https://lain.bgm.tv/pic/cover/c/28/a4/250514_BNBt6.jpg"},"summary":"","name":"3D彼女 リアルガール 第2シリーズ","name_cn":"3D彼女 第二季","tags":[{"name":"恋爱","count":87},{"name":"2019年1月","count":65},{"name":"校园","count":56},{"name":"TV","count":40},{"name":"漫改","count":31},{"name":"漫画改","count":30},{"name":"3D彼女","count":23},{"name":"狗粮","count":20},{"name":"2019","count":15},{"name":"Hoods_Entertainment","count":14},{"name":"HoodsEntertainment","count":10},{"name":"御宅","count":8},{"name":"2019年","count":8},{"name":"续作","count":5},{"name":"日本动画","count":3},{"name":"青春","count":3},{"name":"日本","count":2},{"name":"直谷たかし","count":2},{"name":"芹澤優","count":2},{"name":"动画","count":2},{"name":"二〇一九年","count":2},{"name":"强行喂食","count":1},{"name":"直谷隆","count":1},{"name":"意外还行","count":1},{"name":"【ANIME】TV丨日本","count":1},{"name":"2019年冬季番","count":1},{"name":"【04分】","count":1},{"name":"19-1","count":1},{"name":"2019冬","count":1},{"name":"上西哲平","count":1}],"infobox":[{"key":"中文名","value":"3D彼女 第二季"},{"key":"别名","value":[{"v":"三次元女友 第二季"}]},{"key":"话数","value":"12"},{"key":"放送开始","value":"2019年1月8日"},{"key":"放送星期","value":"星期二"},{"key":"官方网站","value":"http://www.3dkanojo-anime.com/"},{"key":"播放电视台","value":"日本テレビ"},{"key":"播放结束","value":"2019年3月26日"},{"key":"Copyright","value":"©那波マオ／講談社・アニメ「３Ｄ彼女　リアルガール」製作委員会"},{"key":"原作","value":"那波マオ「3D彼女 リアルガール」（講談社「KCデザート」刊）"},{"key":"音乐","value":"Akiyoshi Yasuda"},{"key":"摄影监督","value":"久野充博"}],"rating":{"rank":4684,"total":243,"count":{"1":3,"2":2,"3":3,"4":15,"5":29,"6":82,"7":63,"8":31,"9":6,"10":9},"score":6.4},"total_episodes":12,"collection":{"on_hold":37,"dropped":55,"wish":152,"collect":384,"doing":47},"id":250514,"eps":12,"volumes":0,"locked":false,"nsfw":false,"type":2}