{"date":"2013-12-02","platform":"TV","images":{"small":"https://lain.bgm.tv/r/200/pic/cover/l/db/e4/93377_TEzAK.jpg","grid":"https://lain.bgm.tv/r/100/pic/cover/l/db/e4/93377_TEzAK.jpg","large":"https://lain.bgm.tv/pic/cover/l/db/e4/93377_TEzAK.jpg","medium":"https://lain.bgm.tv/r/800/pic/cover/l/db/e4/93377_TEzAK.jpg","common":"https://lain.bgm.tv/r/400/pic/cover/l/db/e4/93377_TEzAK.jpg"},"summary":"　　天才兼疯子科学家Rick在失踪多年后突然回到女儿Beth的身边，并且在她的车库里搞了一个科学实验室。Rick有一把“传送门枪”，可以穿越到宇宙的各个次元。孙子Morty莫名其妙就成了他的助手，经常被拖进他的自制太空船内，跟他一同开展各种疯狂刺激的宇宙冒险。女儿女婿对他的疯狂行为感到不满，却又对这个天才科学家无可奈何。 ","name":"Rick and Morty Season 1","name_cn":"瑞克和莫蒂 第一季","tags":[{"name":"科幻","count":788},{"name":"美国","count":653},{"name":"脑洞","count":583},{"name":"欧美","count":492},{"name":"TV","count":352},{"name":"搞笑","count":344},{"name":"2013","count":334},{"name":"原创","count":295},{"name":"Rick_and_Morty","count":226},{"name":"神转折","count":173},{"name":"奇诡万变","count":86},{"name":"2013年12月","count":82},{"name":"Adult-Swim","count":71},{"name":"SF","count":35},{"name":"猎奇","count":26},{"name":"美国动画","count":25},{"name":"讽刺","count":16},{"name":"神作","count":12},{"name":"瑞克和莫蒂","count":12},{"name":"Dan_Harmon","count":10},{"name":"AdultSwim","count":9},{"name":"欧美动画","count":7},{"name":"动画","count":7},{"name":"2013年","count":6},{"name":"美漫","count":6},{"name":"奇幻","count":6},{"name":"剧集","count":5},{"name":"JustinRoiland","count":5},{"name":"日常","count":5},{"name":"剧情","count":4}],"infobox":[{"key":"中文名","value":"瑞克和莫蒂 第一季"},{"key":"别名","value":[{"v":"瑞克与莫蒂 第一季"},{"v":"瑞奇和莫迪 第一季"},{"v":"R&M  Season 1"}]},{"key":"话数","value":"11"},{"key":"放送开始","value":"2013年12月2日"},{"key":"官方网站","value":"http://www.rickandmorty.com"},{"key":"播放电视台","value":"Adult Swim"},{"key":"播放结束","value":"2014年4月14日"},{"key":"导演","value":"Justin Roiland、Dan Harmon"},{"key":"演出","value":"Justin Roiland、John Rice、Jeff Myers、Bryan Newton、Stephen Sandoval"},{"key":"脚本","value":"Justin Roiland、Dan Harmon、Tom Kauffman、Ryan Ridley、Wade Randolph、Eric Acosta、Mike McMahan"}],"rating":{"rank":48,"total":3616,"count":{"1":9,"2":2,"3":3,"4":3,"5":24,"6":61,"7":360,"8":1290,"9":1289,"10":575},"score":8.5},"total_episodes":11,"collection":{"on_hold":166,"dropped":76,"wish":763,"collect":5615,"doing":187},"id":93377,"eps":11,"volumes":0,"locked":false,"nsfw":false,"type":2}