{"date":"1988-01-01","platform":"剧场版","images":{"small":"https://lain.bgm.tv/r/200/pic/cover/l/6d/04/105745_X9pO1.jpg","grid":"https://lain.bgm.tv/r/100/pic/cover/l/6d/04/105745_X9pO1.jpg","large":"https://lain.bgm.tv/pic/cover/l/6d/04/105745_X9pO1.jpg","medium":"https://lain.bgm.tv/r/800/pic/cover/l/6d/04/105745_X9pO1.jpg","common":"https://lain.bgm.tv/r/400/pic/cover/l/6d/04/105745_X9pO1.jpg"},"summary":"纪昌是我国古代传说中的人物，在《列子》等古籍中均有记载，日本人中岛敦根据有关传说写成小说《名人传》，该片改编自该小说。 \r\n　　春秋战国时期，赵国首府邯郸有个自小梦想成为天下第一神射手的青年名叫纪昌，他先拜当地的名射手飞卫为师，在飞卫特殊手法的训练下，他在几年后成为技艺与飞卫相当的名射手，但他并不满意，一心想做天下独一无二的神射手，为此甚至想取飞卫的性命，但在又与飞卫较量时，他惭愧地发现师父依旧胜自己一筹。摆脱了危机的飞卫介绍峨眉山上的甘绳老师傅，说自己的箭术和他的相比，完全不值一提，这严重挫伤了纪昌的自尊心。为在箭术上登峰造极，纪昌来到峨眉山，并在甘蝇的教导下，晓得箭术的最高境界是“不射之射”，他做人的理念也自此改变。","name":"不射之射","name_cn":"不射之射","tags":[{"name":"上海美术电影制片厂","count":26,"total_cont":0},{"name":"短片","count":25,"total_cont":0},{"name":"国产","count":20,"total_cont":0},{"name":"1988","count":16,"total_cont":0},{"name":"川本喜八郎","count":16,"total_cont":0},{"name":"剧场版","count":13,"total_cont":0},{"name":"定格动画","count":10,"total_cont":0},{"name":"中日合作","count":8,"total_cont":0},{"name":"小说改","count":6,"total_cont":0},{"name":"动画","count":4,"total_cont":0},{"name":"中国动画","count":3,"total_cont":0},{"name":"中国","count":2,"total_cont":0},{"name":"木偶动画","count":2,"total_cont":0},{"name":"孙道临","count":2,"total_cont":0},{"name":"上美","count":2,"total_cont":0},{"name":"木偶剧","count":2,"total_cont":0},{"name":"85-89","count":1,"total_cont":0},{"name":"木偶","count":1,"total_cont":0},{"name":"待看","count":1,"total_cont":0},{"name":"可独立观赏","count":1,"total_cont":0},{"name":"老害最爱","count":1,"total_cont":0},{"name":"80年代","count":1,"total_cont":0},{"name":"剧场","count":1,"total_cont":0},{"name":"X","count":1,"total_cont":0},{"name":"原创","count":1,"total_cont":0},{"name":"日本动画","count":1,"total_cont":0},{"name":"经典","count":1,"total_cont":0},{"name":"DRAMA","count":1,"total_cont":0},{"name":"合作","count":1,"total_cont":0},{"name":"杂","count":1,"total_cont":0}],"infobox":[{"key":"中文名","value":"不射之射"},{"key":"别名","value":[{"v":"To Shoot Without Shooting"}]},{"key":"上映年度","value":"1988年"},{"key":"片长","value":"25分钟"},{"key":"话数","value":"1"},{"key":"导演","value":"川本喜八郎"},{"key":"脚本","value":"川本喜八郎"}],"rating":{"rank":1934,"total":62,"count":{"1":0,"2":0,"3":2,"4":0,"5":2,"6":11,"7":20,"8":21,"9":4,"10":2},"score":7.2},"total_episodes":1,"collection":{"on_hold":3,"dropped":11,"wish":29,"collect":97,"doing":1},"id":105745,"eps":1,"meta_tags":["剧场版","中国"],"volumes":0,"series":false,"locked":false,"nsfw":false,"type":2}