{"date":"2022-07-04","platform":"TV","images":{"small":"https://lain.bgm.tv/pic/cover/s/68/c0/326869_ogO1g.jpg","grid":"https://lain.bgm.tv/pic/cover/g/68/c0/326869_ogO1g.jpg","large":"https://lain.bgm.tv/pic/cover/l/68/c0/326869_ogO1g.jpg","medium":"https://lain.bgm.tv/pic/cover/m/68/c0/326869_ogO1g.jpg","common":"https://lain.bgm.tv/pic/cover/c/68/c0/326869_ogO1g.jpg"},"summary":"在黑心企业工作的社畜佐野裕司像往常一样带工作回家做。突然，电脑屏幕上出现了一个陌生的窗口。——您，被召唤到异世界了！然后，裕司醒来看见的是，存在着状态数值与技能的异世界。在这个异世界，职业作为“驯魔师”的他，根本难以成为冒险者。但在伙伴史莱姆的帮助下，裕司在一个晚上读完了世界上谁也读不完的魔导书，在不知不觉中取得了“贤者”的副职！虽然获得压倒性力量，裕司却对自己的强大毫无自觉……？最强力量下无意识间成为世上最强！","name":"転生賢者の異世界ライフ～第二の職業を得て、世界最強になりました～","name_cn":"转生贤者的异世界生活～取得第二职业，成为世界最强～","tags":[{"name":"2022年7月","count":85},{"name":"异世界","count":71},{"name":"轻小说改","count":54},{"name":"TV","count":41},{"name":"REVOROOT","count":30},{"name":"龙傲天","count":27},{"name":"2022","count":20},{"name":"奇幻","count":20},{"name":"战斗","count":17},{"name":"轻改","count":14},{"name":"厕纸","count":9},{"name":"小说改","count":6},{"name":"和氣あず未","count":3},{"name":"小嶋慶祐","count":3},{"name":"动画","count":2},{"name":"日本动画","count":2},{"name":"2022年","count":2},{"name":"小林千晃","count":2},{"name":"魔法","count":2},{"name":"穿越","count":2},{"name":"优先级X","count":1},{"name":"厕","count":1},{"name":"一个无聊的套路，人物塑造一般","count":1},{"name":"懒得看","count":1},{"name":"转生贤者的异世界生活～取得第二职业，成为世界最强～","count":1},{"name":"22夏","count":1},{"name":"D01","count":1},{"name":"福島直浩","count":1},{"name":"日本","count":1},{"name":"TVA","count":1}],"infobox":[{"key":"中文名","value":"转生贤者的异世界生活～取得第二职业，成为世界最强～"},{"key":"别名","value":[{"v":"转生贤者的异世界生活～获得第二职业并成为世界最强～"},{"v":"My Isekai Life: I Gained a Second Class and Became the Strongest Sage in the World!"},{"v":"Tensei Kenja no Isekai Life - Daini no Shokugyo wo Ete, Sekai Saikyou ni Narimashita"}]},{"key":"话数","value":"12"},{"key":"放送开始","value":"2022年7月4日"},{"key":"放送星期","value":"星期一"},{"key":"官方网站","value":"https://tenseikenja.com/"},{"key":"播放电视台","value":"AT-X"},{"key":"其他电视台","value":"TOKYO MX / BS日テレ / BSフジ"},{"key":"Copyright","value":"© 進行諸島・SBクリエイティブ／転生賢者の製作委員会"},{"key":"原作","value":"進行諸島（GA ノベル／SB クリエイティブ刊）"},{"key":"人物原案","value":"風花風花"},{"key":"导演","value":"小嶋慶祐"},{"key":"音乐","value":"吟(BUSTED ROSE)"},{"key":"人物设定","value":"小嶋慶祐、埼玉憲人"},{"key":"系列构成","value":"福島直浩"},{"key":"美术监督","value":"平良亜以子 (スタジオなや)"},{"key":"色彩设计","value":"竹澤聡"},{"key":"总作画监督","value":"埼玉憲人、後藤圭佑"},{"key":"摄影监督","value":"小林俊介 （サンジゲン）"},{"key":"音响监督","value":"田中亮"},{"key":"音乐制作","value":"ポニーキャニオン"},{"key":"动画制作","value":"REVOROOT"},{"key":"副导演","value":"鈴木清崇"},{"key":"企画","value":"大熊一成、北村州識、宿輪浩介、阿部隆二、里見治紀、伊藤幸弘、久保田暁、國枝信吾"},{"key":"制片人","value":"松岡貴徳、秋田規行、成田明浩、藤村智子、加瀨直人(加瀬直人)、大森慎司、丸山創、外川明宏；动画制片人：江波和樹"},{"key":"剪辑","value":"増永純一"}],"rating":{"rank":6947,"total":148,"count":{"1":13,"2":7,"3":16,"4":33,"5":29,"6":37,"7":6,"8":2,"9":1,"10":4},"score":4.6},"total_episodes":12,"collection":{"on_hold":21,"dropped":111,"wish":117,"collect":24,"doing":448},"id":326869,"eps":12,"volumes":0,"locked":false,"nsfw":false,"type":2}