{"date":"1999-10-13","platform":"TV","images":{"small":"https://lain.bgm.tv/r/200/pic/cover/l/8a/0e/697_7hDJH.jpg","grid":"https://lain.bgm.tv/r/100/pic/cover/l/8a/0e/697_7hDJH.jpg","large":"https://lain.bgm.tv/pic/cover/l/8a/0e/697_7hDJH.jpg","medium":"https://lain.bgm.tv/r/800/pic/cover/l/8a/0e/697_7hDJH.jpg","common":"https://lain.bgm.tv/r/400/pic/cover/l/8a/0e/697_7hDJH.jpg"},"summary":"帕拉蒂姆城里的所有人都失去了40年前的记忆，而居民们用头脑中留下的文明和道德观念维系着这个失忆之城。谈判专家罗杰·史密斯自救下机器人R·多洛茜·薇恩莱特后又经历了一系列的冒险，渐渐接近了这个世界的真实……","name":"THE ビッグオー","name_cn":"THE BIG-O","tags":[{"name":"SUNRISE","count":400},{"name":"萝卜","count":282},{"name":"TV","count":237},{"name":"1999","count":198},{"name":"科幻","count":168},{"name":"原创","count":154},{"name":"美式风格","count":149},{"name":"片山一良","count":124},{"name":"The_Big_O","count":89},{"name":"小中千昭","count":76},{"name":"机器人","count":71},{"name":"SF","count":36},{"name":"大圈","count":33},{"name":"showtime！","count":30},{"name":"1999年10月","count":28},{"name":"机战","count":19},{"name":"90年代","count":16},{"name":"记忆","count":13},{"name":"TVA","count":6},{"name":"Andriod","count":5},{"name":"1990s","count":5},{"name":"剧情","count":4},{"name":"半年番","count":4},{"name":"日本","count":4},{"name":"矢島晶子","count":3},{"name":"robo","count":3},{"name":"佐藤顺一","count":3},{"name":"2003","count":3},{"name":"补番","count":3},{"name":"日本动画","count":3}],"infobox":[{"key":"中文名","value":"THE BIG-O"},{"key":"别名","value":[{"v":"THE BIG O"},{"v":"魅影巨神"},{"v":"ザ ビッグオー"}]},{"key":"话数","value":"26"},{"key":"放送开始","value":"1999年10月13日"},{"key":"官方网站","value":"http://www.the-big-o.net/"},{"key":"播放结束","value":"2003年3月27日"},{"key":"导演","value":"片山一良"},{"key":"音乐","value":"佐橋俊彦"},{"key":"其他","value":"1999年10月13日 - 2000年1月19日（第1期・13话） / 2003年1月2日 - 3月27日（第2期・13话）"},{"key":"企画","value":"サンライズ"},{"key":"原作","value":"矢立肇、片山一良"},{"key":"系列构成","value":"小中千昭、片山一良"},{"key":"人物设定","value":"さとうけいいち"},{"key":"机械设定","value":"さとうけいいち"},{"key":"美术监督","value":"太田大、加藤浩（辅）"},{"key":"色彩设计","value":"片山由美子（S1）、中里智恵、村上智美（S1）"},{"key":"动画制作","value":"サンライズ"},{"key":"音响监督","value":"鶴岡陽太"},{"key":"摄影监督","value":"桶田一展（S1）、福士享（S2）"},{"key":"设定","value":"さとうけいいち 设计协力：籬讒賊、宮尾佳和"},{"key":"剪辑","value":"鶴渕友彰（S1）、山森重之[ジェイ・フィルム]（S2）"},{"key":"音乐制作人","value":"野崎圭一（ビクターエンターテインメント）"},{"key":"音效","value":"野口透[アニメサウンド]（S1）、庄司雅弘[フィズサウンド]（S2）"},{"key":"音乐制作","value":"ビクターエンタテインメント、WOWOWミュージック・イン"},{"key":"特效","value":"干場豊（マリックス）"},{"key":"制片人","value":"杉田敦（バンダイビジュアル）、指田英司、大橋千恵雄、内田健二（S2）"},{"key":"助理制片人","value":"国崎久徳（バンダイビジュアル）、石川達大（S2）"},{"key":"製作","value":"サンライズ、バンダイビジュアル、Cartoon Network Studios（S2）"},{"key":"脚本","value":"小中千昭、長谷川圭一、赤星政尚、吉田伸"},{"key":"分镜","value":"片山一良、松園公、飯田馬之介、岡本英樹、山下明彦、渡邊哲哉、米たにヨシトモ、喜多幡徹、寺東克己、西澤晋、甚目喜一（佐藤順一）"},{"key":"演出","value":"佐藤育郎、喜多幡徹、渡邊哲哉、岡本英樹、小原正和、渡辺純央、中村健治、吉村章"},{"key":"作画监督","value":"小曽根正美、平山円、堀井久美、しんぼたくろう （中村プロ）、羽山賢二、竹内浩志、吉田徹、森下博光、中山岳洋、吉崎誠、羽山淳一、永田正美"},{"key":"机械作画监督","value":"宮澤努、米山浩平（中村プロ）、桝田浩史、鈴木勤、仲盛文、安藤義信、城前龍治、まさひろ山根（山根理宏）、中山久司（森久司）、伊藤浩二、吉田徹"},{"key":"主题歌演出","value":"永井ルイ（OP）、ROBBIE DANZIE with 高尾直樹（ED）"},{"key":"主题歌作词","value":"永井ルイ（OP1、BD版OP）、Chie（ED）"},{"key":"主题歌作曲","value":"永井ルイ（OP1、BD版OP）、佐橋俊彦（OP2）、島健（ED）"},{"key":"主题歌编曲","value":"永井ルイ（OP1、BD版OP）、佐橋俊彦（OP2）、島健（ED）"}],"rating":{"rank":343,"total":881,"count":{"1":3,"2":0,"3":1,"4":10,"5":17,"6":42,"7":198,"8":369,"9":184,"10":57},"score":7.9},"total_episodes":26,"collection":{"on_hold":175,"dropped":56,"wish":1396,"collect":1127,"doing":176},"id":697,"eps":26,"volumes":0,"series":false,"locked":false,"nsfw":false,"type":2}