{"date":"2023-10-01","platform":"TV","images":{"small":"https://lain.bgm.tv/r/200/pic/cover/l/bc/4b/400551_O4R7O.jpg","grid":"https://lain.bgm.tv/r/100/pic/cover/l/bc/4b/400551_O4R7O.jpg","large":"https://lain.bgm.tv/pic/cover/l/bc/4b/400551_O4R7O.jpg","medium":"https://lain.bgm.tv/r/800/pic/cover/l/bc/4b/400551_O4R7O.jpg","common":"https://lain.bgm.tv/r/400/pic/cover/l/bc/4b/400551_O4R7O.jpg"},"summary":"某天，独居在森林里的魔女「艾丽莎」捡到了人类婴儿。虽然艾丽莎不知该如何是好，仍替婴儿取名为「薇奥拉」，并决定扶养她。十六年后，薇奥拉不只变成超级恋母的女孩，连成长幅度都超乎预料……等等，长太大只了啦～！！\r\n娇小可爱的魔女妈妈，与高挑丰满的人类女儿！颠覆外表印象的魔女亲子档的温馨搞笑喜剧登场！","name":"でこぼこ魔女の親子事情","name_cn":"凹凸魔女的母女故事","tags":[{"name":"2023年10月","count":222},{"name":"搞笑","count":211},{"name":"百合","count":151},{"name":"漫画改","count":140},{"name":"日常","count":130},{"name":"TV","count":103},{"name":"奇幻","count":73},{"name":"A-Real","count":67},{"name":"漫改","count":66},{"name":"2023","count":65},{"name":"古賀葵","count":35},{"name":"水樹奈々","count":27},{"name":"治愈","count":14},{"name":"2023年","count":9},{"name":"异世界","count":6},{"name":"2023年秋","count":6},{"name":"未确定","count":5},{"name":"A-real","count":5},{"name":"魔女","count":4},{"name":"亲情","count":4},{"name":"萌","count":3},{"name":"母女","count":3},{"name":"たかたまさひろ","count":3},{"name":"高田真宏","count":2},{"name":"轻松","count":2},{"name":"日本","count":2},{"name":"可独立观赏","count":2},{"name":"凹凸魔女的母女故事","count":2},{"name":"ジャイロナックル","count":2},{"name":"TVA","count":2}],"infobox":[{"key":"中文名","value":"凹凸魔女的母女故事"},{"key":"别名","value":[{"v":"凹凸魔女的親子日常"},{"v":"Dekoboko Majo no Oyako Jijou"},{"v":"The Family Circumstances of the Irregular Witch"}]},{"key":"话数","value":"12"},{"key":"放送开始","value":"2023年10月1日"},{"key":"放送星期","value":"星期日"},{"key":"官方网站","value":"https://dekoboko-majo-anime.jp/"},{"key":"播放电视台","value":"TOKYO MX"},{"key":"其他电视台","value":"BSフジ / AT-X"},{"key":"播放结束","value":"2023年12月10日（网络配信）2023年12月17日（TV）"},{"key":"其他","value":"dアニメストア第2话起一周先行配信"},{"key":"Copyright","value":"©ピロヤ・COMICメテオ／でこぼこ魔女製作委員会"},{"key":"原作","value":"ピロヤ（「COMICメテオ」連載）"},{"key":"导演","value":"たかたまさひろ"},{"key":"人物设定","value":"吉田美和"},{"key":"系列构成","value":"ジャイロナックル"},{"key":"色彩设计","value":"中村里沙"},{"key":"剪辑","value":"宇都宮正記(ゼロジー)"},{"key":"製作","value":"でこぼこ魔女製作委員会（読売テレビエンタープライズ、キングレコード、BookLive!、A-real、ハピネットファントム・スタジオ、日活）"},{"key":"企画","value":"薮下維也、松下卓也、淡野正、山浦貴法、小西啓介、鳥羽乾二郎；企画协力：江波戸憲司"},{"key":"执行制片人","value":"梅本享、中西豪、野淵大輔、林宏之"},{"key":"制片人","value":"佐藤友紀、藤井貴大、川野和貴、前田健太、結城未来"},{"key":"副制片人","value":"栗田ひろ子、桒原和也"},{"key":"音乐制作","value":"キングレコード"},{"key":"动画制片人","value":"山浦貴法"}],"rating":{"rank":6688,"total":707,"count":{"1":1,"2":4,"3":12,"4":39,"5":138,"6":288,"7":186,"8":27,"9":3,"10":9},"score":6},"total_episodes":13,"collection":{"on_hold":135,"dropped":297,"wish":315,"collect":820,"doing":322},"id":400551,"eps":12,"volumes":0,"series":false,"locked":false,"nsfw":false,"type":2}