{"date":"2013-07-17","platform":"剧场版","images":{"small":"https://lain.bgm.tv/r/200/pic/cover/l/33/0e/84189_91mC4.jpg","grid":"https://lain.bgm.tv/r/100/pic/cover/l/33/0e/84189_91mC4.jpg","large":"https://lain.bgm.tv/pic/cover/l/33/0e/84189_91mC4.jpg","medium":"https://lain.bgm.tv/r/800/pic/cover/l/33/0e/84189_91mC4.jpg","common":"https://lain.bgm.tv/r/400/pic/cover/l/33/0e/84189_91mC4.jpg"},"summary":"菜园蜗牛Turbo抱有一个几乎不可能实现的梦想：成为汽车大赛的冠军。一次偶然的不寻常事件让他拥有了非凡的速度，Turbo打算让自己的梦想成真。","name":"Turbo","name_cn":"极速蜗牛","tags":[{"name":"欧美","count":56},{"name":"梦工厂","count":51},{"name":"剧场版","count":43},{"name":"动画电影","count":26},{"name":"2013","count":22},{"name":"竞速","count":19},{"name":"搞笑","count":18},{"name":"美国","count":15},{"name":"原创","count":15},{"name":"3D","count":12},{"name":"DreamWorks","count":6},{"name":"2015年12月","count":5},{"name":"2013年","count":3},{"name":"动画","count":2},{"name":"DreamWorks_Animation","count":2},{"name":"2010-2019","count":2},{"name":"美国动画","count":1},{"name":"竞技","count":1},{"name":"欧美电影","count":1},{"name":"欧美动画电影","count":1},{"name":"欧美剧场版","count":1},{"name":"极速蜗牛","count":1},{"name":"塞缪尔杰克逊","count":1},{"name":"DreamWorksAnimation","count":1},{"name":"2013年7月","count":1},{"name":"2010s","count":1}],"infobox":[{"key":"中文名","value":"极速蜗牛"},{"key":"别名","value":[{"v":"极速turbo"},{"v":"涡轮方程式"}]},{"key":"上映年度","value":"2013年7月17日"},{"key":"片长","value":"96min"},{"key":"官方网站","value":"www.turbomovie.com"},{"key":"其他","value":"2013年9月18日中国大陆上映"},{"key":"国家","value":"美国"},{"key":"语言","value":"英语"},{"key":"製作","value":"DreamWorks Animation SKG"},{"key":"IMDb_id","value":"tt1860353"},{"key":"话数","value":"1"}],"rating":{"rank":5312,"total":168,"count":{"1":1,"2":1,"3":1,"4":8,"5":20,"6":69,"7":47,"8":19,"9":1,"10":1},"score":6.3},"total_episodes":1,"collection":{"on_hold":4,"dropped":12,"wish":21,"collect":364,"doing":5},"id":84189,"eps":1,"volumes":0,"series":false,"locked":false,"nsfw":false,"type":2}